api_error_monitor/__init__.py
api_error_monitor/core.py
api_error_monitor/decorators.py
api_error_monitor-1.0.4.dist-info/licenses/LICENSE
api_error_monitor-1.0.4.dist-info/METADATA
api_error_monitor-1.0.4.dist-info/WHEEL
api_error_monitor-1.0.4.dist-info/top_level.txt
api_error_monitor-1.0.4.dist-info/RECORD
